<pages has_audio="1" background="default.jpg" scale="1.6" valign="top" halign="center" line_spacing="40" characters_per_row="6" rows_per_page="10" position_x="3" position_y="40" style="1">

  <page background="" audio_file="" style="6" align="left" line_spacing="50" scale="1.6" position_y="-16" position_x="3" characters_per_row="6" rows_per_page="10" halign="center" valign="middle" gameParagraph="4,7,4">

    <cue_points>
2728.80,3099.23,3333.83,3589.01,4651.11,5009.18,5268.28,5729.25,5889.97,6087.33,6396.02,6774.67,6984.38,7293.06,7540.02</cue_points>

    <paragraph align="left" style="0">

      <zi han_zi="战" pin_yin="zhan" sheng_diao="4" id="372" mistakes="0" times="0" xu_hao="0" qs="0"/>

      <zi han_zi="国" pin_yin="guo" sheng_diao="2" id="320" mistakes="0" times="0" xu_hao="1" qs="0"/>

      <zi han_zi="时" pin_yin="shi" sheng_diao="2" id="1523" mistakes="0" times="0" xu_hao="2" qs="0"/>

      <zi han_zi="期" pin_yin="qi" sheng_diao="1" id="486" mistakes="0" times="0" xu_hao="3" qs="0"/>

      <zi han_zi="，" pin_yin="" sheng_diao="" id="" mistakes="0" times="0" xu_hao="4" qs="0"/>

      <zi han_zi="齐" pin_yin="qi" sheng_diao="2" id="2038" mistakes="0" times="0" xu_hao="5" qs="0"/>

      <zi han_zi="威" pin_yin="wei" sheng_diao="1" id="2373" mistakes="0" times="0" xu_hao="6" qs="0"/>

      <zi han_zi="王" pin_yin="wang" sheng_diao="2" id="1725" mistakes="0" times="0" xu_hao="7" qs="0"/>

      <zi han_zi="继" pin_yin="ji" sheng_diao="4" id="1466" mistakes="0" times="0" xu_hao="8" qs="0"/>

      <zi han_zi="承" pin_yin="cheng" sheng_diao="2" id="2085" mistakes="0" times="0" xu_hao="9" qs="0"/>

      <zi han_zi="王" pin_yin="wang" sheng_diao="2" id="1725" mistakes="0" times="0" xu_hao="10" qs="0"/>

      <zi han_zi="位" pin_yin="wei" sheng_diao="4" id="233" mistakes="0" times="0" xu_hao="11" qs="0"/>

      <zi han_zi="已" pin_yin="yi" sheng_diao="3" id="1472" mistakes="0" times="0" xu_hao="12" qs="0"/>

      <zi han_zi="有" pin_yin="you" sheng_diao="3" id="282" mistakes="0" times="0" xu_hao="13" qs="0"/>

      <zi han_zi="三" pin_yin="san" sheng_diao="1" id="1998" mistakes="0" times="0" xu_hao="14" qs="0"/>

      <zi han_zi="年" pin_yin="nian" sheng_diao="2" id="143" mistakes="0" times="0" xu_hao="15" qs="0"/>

      <zi han_zi="。" pin_yin="" sheng_diao="" id="" mistakes="0" times="0" xu_hao="16" qs="0"/>

    </paragraph>

  </page>

  <page background="" audio_file="" style="6" align="left" line_spacing="50" scale="1.8" position_y="-16" position_x="3" characters_per_row="8" halign="center" valign="middle" rows_per_page="10" gameParagraph="">

    <cue_points>
654.04,870.69,1827.43,2027.53,2330.02,2693.83,2935.21,3323.34,3654.45,4284.17,4500.82,4700.92,5109.69</cue_points>

    <paragraph align="left" style="0">

      <zi han_zi="可" pin_yin="ke" sheng_diao="3" id="2041" mistakes="0" times="0" xu_hao="0" qs="0"/>

      <zi han_zi="是" pin_yin="shi" sheng_diao="4" id="2147" mistakes="0" times="0" xu_hao="1" qs="0"/>

      <zi han_zi="他" pin_yin="ta" sheng_diao="1" id="2179" mistakes="0" times="0" xu_hao="2" qs="0"/>

      <zi han_zi="整" pin_yin="zheng" sheng_diao="3" id="554" mistakes="0" times="0" xu_hao="3" qs="0"/>

      <zi han_zi="天" pin_yin="tian" sheng_diao="1" id="325" mistakes="0" times="0" xu_hao="4" qs="0"/>

      <zi han_zi="饮" pin_yin="yin" sheng_diao="3" id="1273" mistakes="0" times="0" xu_hao="5" qs="0"/>

      <zi han_zi="酒" pin_yin="jiu" sheng_diao="3" id="965" mistakes="0" times="0" xu_hao="6" qs="0"/>

      <zi han_zi="作" pin_yin="zuo" sheng_diao="4" id="120" mistakes="0" times="0" xu_hao="7" qs="0"/>

      <zi han_zi="乐" pin_yin="le" sheng_diao="4" id="982" mistakes="0" times="0" xu_hao="8" qs="0"/>

      <zi han_zi="，" pin_yin="" sheng_diao="" id="" mistakes="0" times="0" xu_hao="9" qs="0"/>

      <zi han_zi="不" pin_yin="bu" sheng_diao="4" id="86" mistakes="0" times="0" xu_hao="10" qs="0"/>

      <zi han_zi="理" pin_yin="li" sheng_diao="3" id="2188" mistakes="0" times="0" xu_hao="11" qs="0"/>

      <zi han_zi="朝" pin_yin="chao" sheng_diao="2" id="643" mistakes="0" times="0" xu_hao="12" qs="0"/>

      <zi han_zi="政" pin_yin="zheng" sheng_diao="4" id="2279" mistakes="0" times="0" xu_hao="13" qs="0"/>

      <zi han_zi="。" pin_yin="" sheng_diao="" id="" mistakes="0" times="0" xu_hao="14" qs="0"/>

    </paragraph>

  </page>

  <page background="" audio_file="" style="6" align="left" line_spacing="50" scale="1.6" position_y="-16" position_x="3" characters_per_row="9" halign="center" valign="middle" rows_per_page="10" gameParagraph="">

    <cue_points>
1033.85,1317.33,1650.83,1992.67,2247.17,3068.21,3368.36,3468.41,3701.86,3964.50,4269.03,4481.42,4689.86,4881.63,5085.90,5344.36</cue_points>

    <paragraph align="left" style="0">

      <zi han_zi="大" pin_yin="da" sheng_diao="4" id="430" mistakes="0" times="0" xu_hao="0" qs="0"/>

      <zi han_zi="臣" pin_yin="chen" sheng_diao="2" id="655" mistakes="0" times="0" xu_hao="1" qs="0"/>

      <zi han_zi="淳" pin_yin="chun" sheng_diao="2" id="2584" mistakes="0" times="0" xu_hao="2" qs="0"/>

      <zi han_zi="于" pin_yin="yv" sheng_diao="2" id="1992" mistakes="0" times="0" xu_hao="3" qs="0"/>

      <zi han_zi="髡" pin_yin="kun" sheng_diao="1" id="2585" mistakes="0" times="0" xu_hao="4" qs="0"/>

      <zi han_zi="想" pin_yin="xiang" sheng_diao="3" id="90" mistakes="0" times="0" xu_hao="5" qs="0"/>

      <zi han_zi="了" pin_yin="le" sheng_diao="0" id="50" mistakes="0" times="0" xu_hao="6" qs="0"/>

      <zi han_zi="个" pin_yin="ge" sheng_diao="4" id="2182" mistakes="0" times="0" xu_hao="7" qs="0"/>

      <zi han_zi="激" pin_yin="ji" sheng_diao="1" id="327" mistakes="0" times="0" xu_hao="8" qs="0"/>

      <zi han_zi="励" pin_yin="li" sheng_diao="4" id="328" mistakes="0" times="0" xu_hao="9" qs="0"/>

      <zi han_zi="齐" pin_yin="qi" sheng_diao="2" id="2038" mistakes="0" times="0" xu_hao="10" qs="0"/>

      <zi han_zi="威" pin_yin="wei" sheng_diao="1" id="2373" mistakes="0" times="0" xu_hao="11" qs="0"/>

      <zi han_zi="王" pin_yin="wang" sheng_diao="2" id="1725" mistakes="0" times="0" xu_hao="12" qs="0"/>

      <zi han_zi="的" pin_yin="de" sheng_diao="0" id="2626" mistakes="0" times="0" xu_hao="13" qs="0"/>

      <zi han_zi="办" pin_yin="ban" sheng_diao="4" id="619" mistakes="0" times="0" xu_hao="14" qs="0"/>

      <zi han_zi="法" pin_yin="fa" sheng_diao="3" id="1812" mistakes="0" times="0" xu_hao="15" qs="0"/>

      <zi han_zi="。" pin_yin="" sheng_diao="" id="" mistakes="0" times="0" xu_hao="16" qs="0"/>

    </paragraph>

  </page>

  <page background="" audio_file="" style="6" align="left" line_spacing="25" scale="1.5" position_y="-16" position_x="3" characters_per_row="10" halign="center" valign="middle" rows_per_page="10" gameParagraph="14,8">

    <cue_points>
478.72,709.82,1663.12,1968.51,2731.98,3086.89,3379.90,4201.14,4593.40,4972.86,5088.42,5216.55,5369.04,5624.91,6788.68,7003.28,7255.02,7907.27,8233.08,8616.88,8922.27,9155.43</cue_points>

    <paragraph align="left" style="0">

      <zi han_zi="他" pin_yin="ta" sheng_diao="1" id="2179" mistakes="0" times="0" xu_hao="0" qs="0"/>

      <zi han_zi="说" pin_yin="shuo" sheng_diao="1" id="2037" mistakes="0" times="0" xu_hao="1" qs="0"/>

      <zi han_zi="：" pin_yin="" sheng_diao="" id="" mistakes="0" times="0" xu_hao="2" qs="0"/>

      <zi han_zi="“" pin_yin="" sheng_diao="" id="" mistakes="0" times="0" xu_hao="3" qs="0"/>

      <zi han_zi="大" pin_yin="da" sheng_diao="4" id="430" mistakes="0" times="0" xu_hao="4" qs="0"/>

      <zi han_zi="王" pin_yin="wang" sheng_diao="2" id="1725" mistakes="0" times="0" xu_hao="5" qs="0"/>

      <zi han_zi="，" pin_yin="" sheng_diao="" id="" mistakes="0" times="0" xu_hao="6" qs="0"/>

      <zi han_zi="臣" pin_yin="chen" sheng_diao="2" id="655" mistakes="0" times="0" xu_hao="7" qs="0"/>

      <zi han_zi="听" pin_yin="ting" sheng_diao="1" id="592" mistakes="0" times="0" xu_hao="8" qs="0"/>

      <zi han_zi="说" pin_yin="shuo" sheng_diao="1" id="2037" mistakes="0" times="0" xu_hao="9" qs="0"/>

      <zi han_zi="，" pin_yin="" sheng_diao="" id="" mistakes="0" times="0" xu_hao="10" qs="0"/>

      <zi han_zi="齐" pin_yin="qi" sheng_diao="2" id="2038" mistakes="0" times="0" xu_hao="11" qs="0"/>

      <zi han_zi="国" pin_yin="guo" sheng_diao="2" id="320" mistakes="0" times="0" xu_hao="12" qs="0"/>

      <zi han_zi="有" pin_yin="you" sheng_diao="3" id="282" mistakes="0" times="0" xu_hao="13" qs="0"/>

      <zi han_zi="一" pin_yin="yi" sheng_diao="4" id="2089" mistakes="0" times="0" xu_hao="14" qs="0"/>

      <zi han_zi="只" pin_yin="zhi" sheng_diao="1" id="2526" mistakes="0" times="0" xu_hao="15" qs="0"/>

      <zi han_zi="大" pin_yin="da" sheng_diao="4" id="430" mistakes="0" times="0" xu_hao="16" qs="0"/>

      <zi han_zi="鸟" pin_yin="niao" sheng_diao="3" id="2201" mistakes="0" times="0" xu_hao="17" qs="0"/>

      <zi han_zi="，" pin_yin="" sheng_diao="" id="" mistakes="0" times="0" xu_hao="18" qs="0"/>

      <zi han_zi="三" pin_yin="san" sheng_diao="1" id="1998" mistakes="0" times="0" xu_hao="19" qs="0"/>

      <zi han_zi="年" pin_yin="nian" sheng_diao="2" id="143" mistakes="0" times="0" xu_hao="20" qs="0"/>

      <zi han_zi="来" pin_yin="lai" sheng_diao="2" id="1003" mistakes="0" times="0" xu_hao="21" qs="0"/>

      <zi han_zi="不" pin_yin="bu" sheng_diao="4" id="86" mistakes="0" times="0" xu_hao="22" qs="0"/>

      <zi han_zi="飞" pin_yin="fei" sheng_diao="1" id="415" mistakes="0" times="0" xu_hao="23" qs="0"/>

      <zi han_zi="也" pin_yin="ye" sheng_diao="3" id="2169" mistakes="0" times="0" xu_hao="24" qs="0"/>

      <zi han_zi="不" pin_yin="bu" sheng_diao="2" id="2609" mistakes="0" times="0" xu_hao="25" qs="0"/>

      <zi han_zi="叫" pin_yin="jiao" sheng_diao="4" id="803" mistakes="0" times="0" xu_hao="26" qs="0"/>

      <zi han_zi="。" pin_yin="" sheng_diao="" id="" mistakes="0" times="0" xu_hao="27" qs="0"/>

      <zi han_zi="”" pin_yin="" sheng_diao="" id="" mistakes="0" times="0" xu_hao="28" qs="0"/>

    </paragraph>

  </page>

  <page background="" audio_file="" style="6" align="left" line_spacing="25" scale="1.5" position_y="-16" position_x="3" characters_per_row="10" halign="center" valign="middle" rows_per_page="10" gameParagraph="12,11">

    <cue_points>
977.09,1409.97,1607.86,1966.54,2205.66,2436.53,2617.93,2820.15,3582.65,4048.52,4258.77,4469.03,5479.10,5709.97,5928.68,6155.23,6992.14,7301.35,7499.24,7721.86,7923.88,8180.10,8394.69</cue_points>

    <paragraph align="left" style="0">

      <zi han_zi="他" pin_yin="ta" sheng_diao="1" id="2179" mistakes="0" times="0" xu_hao="0" qs="0"/>

      <zi han_zi="故" pin_yin="gu" sheng_diao="4" id="236" mistakes="0" times="0" xu_hao="1" qs="0"/>

      <zi han_zi="意" pin_yin="yi" sheng_diao="4" id="713" mistakes="0" times="0" xu_hao="2" qs="0"/>

      <zi han_zi="停" pin_yin="ting" sheng_diao="2" id="88" mistakes="0" times="0" xu_hao="3" qs="0"/>

      <zi han_zi="顿" pin_yin="dun" sheng_diao="4" id="2461" mistakes="0" times="0" xu_hao="4" qs="0"/>

      <zi han_zi="了" pin_yin="le" sheng_diao="0" id="50" mistakes="0" times="0" xu_hao="5" qs="0"/>

      <zi han_zi="一" pin_yin="yi" sheng_diao="2" id="2197" mistakes="0" times="0" xu_hao="6" qs="0"/>

      <zi han_zi="下" pin_yin="xia" sheng_diao="4" id="868" mistakes="0" times="0" xu_hao="7" qs="0"/>

      <zi han_zi="，" pin_yin="" sheng_diao="" id="" mistakes="0" times="0" xu_hao="8" qs="0"/>

      <zi han_zi="试" pin_yin="shi" sheng_diao="4" id="1448" mistakes="0" times="0" xu_hao="9" qs="0"/>

      <zi han_zi="探" pin_yin="tan" sheng_diao="4" id="1217" mistakes="0" times="0" xu_hao="10" qs="0"/>

      <zi han_zi="着" pin_yin="zhe" sheng_diao="0" id="45" mistakes="0" times="0" xu_hao="11" qs="0"/>

      <zi han_zi="问" pin_yin="wen" sheng_diao="4" id="126" mistakes="0" times="0" xu_hao="12" qs="0"/>

      <zi han_zi="：" pin_yin="" sheng_diao="" id="" mistakes="0" times="0" xu_hao="13" qs="0"/>

      <zi han_zi="“" pin_yin="" sheng_diao="" id="" mistakes="0" times="0" xu_hao="14" qs="0"/>

      <zi han_zi="大" pin_yin="da" sheng_diao="4" id="430" mistakes="0" times="0" xu_hao="15" qs="0"/>

      <zi han_zi="王" pin_yin="wang" sheng_diao="2" id="1725" mistakes="0" times="0" xu_hao="16" qs="0"/>

      <zi han_zi="知" pin_yin="zhi" sheng_diao="1" id="929" mistakes="0" times="0" xu_hao="17" qs="0"/>

      <zi han_zi="道" pin_yin="dao" sheng_diao="4" id="1014" mistakes="0" times="0" xu_hao="18" qs="0"/>

      <zi han_zi="，" pin_yin="" sheng_diao="" id="" mistakes="0" times="0" xu_hao="19" qs="0"/>

      <zi han_zi="这" pin_yin="zhe" sheng_diao="4" id="2175" mistakes="0" times="0" xu_hao="20" qs="0"/>

      <zi han_zi="是" pin_yin="shi" sheng_diao="4" id="2147" mistakes="0" times="0" xu_hao="21" qs="0"/>

      <zi han_zi="一" pin_yin="yi" sheng_diao="4" id="2089" mistakes="0" times="0" xu_hao="22" qs="0"/>

      <zi han_zi="只" pin_yin="zhi" sheng_diao="1" id="2526" mistakes="0" times="0" xu_hao="23" qs="0"/>

      <zi han_zi="什" pin_yin="shen" sheng_diao="2" id="2750" mistakes="0" times="0" xu_hao="24" qs="0"/>

      <zi han_zi="么" pin_yin="me" sheng_diao="0" id="2622" mistakes="0" times="0" xu_hao="25" qs="0"/>

      <zi han_zi="鸟" pin_yin="niao" sheng_diao="3" id="2201" mistakes="0" times="0" xu_hao="26" qs="0"/>

      <zi han_zi="？" pin_yin="" sheng_diao="" id="" mistakes="0" times="0" xu_hao="27" qs="0"/>

      <zi han_zi="”" pin_yin="" sheng_diao="" id="" mistakes="0" times="0" xu_hao="28" qs="0"/>

    </paragraph>

  </page>

  <page background="" audio_file="" style="10" align="left" line_spacing="25" scale="1.5" position_y="-16" position_x="3" characters_per_row="9" halign="center" valign="middle" rows_per_page="10" gameParagraph="13,7">

    <cue_points>
1975.61,2175.98,2300.20,2504.58,2873.25,3678.72,3987.28,4159.60,4592.39,4872.90,5029.19,5281.65,5598.23,6463.81,6620.09,6868.55,7129.02,7625.93,7850.54,8006.83</cue_points>

    <paragraph align="left" style="0">

      <zi han_zi="齐" pin_yin="qi" sheng_diao="2" id="2038" mistakes="0" times="0" xu_hao="0" qs="0"/>

      <zi han_zi="威" pin_yin="wei" sheng_diao="1" id="2373" mistakes="0" times="0" xu_hao="1" qs="0"/>

      <zi han_zi="王" pin_yin="wang" sheng_diao="2" id="1725" mistakes="0" times="0" xu_hao="2" qs="0"/>

      <zi han_zi="知" pin_yin="zhi" sheng_diao="1" id="929" mistakes="0" times="0" xu_hao="3" qs="0"/>

      <zi han_zi="道" pin_yin="dao" sheng_diao="4" id="1014" mistakes="0" times="0" xu_hao="4" qs="0"/>

      <zi han_zi="淳" pin_yin="chun" sheng_diao="2" id="2584" mistakes="0" times="0" xu_hao="5" qs="0"/>

      <zi han_zi="于" pin_yin="yv" sheng_diao="2" id="1992" mistakes="0" times="0" xu_hao="6" qs="0"/>

      <zi han_zi="髡" pin_yin="kun" sheng_diao="1" id="2585" mistakes="0" times="0" xu_hao="7" qs="0"/>

      <zi han_zi="在" pin_yin="zai" sheng_diao="4" id="780" mistakes="0" times="0" xu_hao="8" qs="0"/>

      <zi han_zi="暗" pin_yin="an" sheng_diao="4" id="1066" mistakes="0" times="0" xu_hao="9" qs="0"/>

      <zi han_zi="喻" pin_yin="yv" sheng_diao="4" id="2586" mistakes="0" times="0" xu_hao="10" qs="0"/>

      <zi han_zi="自" pin_yin="zi" sheng_diao="4" id="628" mistakes="0" times="0" xu_hao="11" qs="0"/>

      <zi han_zi="己" pin_yin="ji" sheng_diao="3" id="629" mistakes="0" times="0" xu_hao="12" qs="0"/>

      <zi han_zi="，" pin_yin="" sheng_diao="" id="" mistakes="0" times="0" xu_hao="13" qs="0"/>

      <zi han_zi="不" pin_yin="bu" sheng_diao="4" id="86" mistakes="0" times="0" xu_hao="14" qs="0"/>

      <zi han_zi="由" pin_yin="you" sheng_diao="2" id="2100" mistakes="0" times="0" xu_hao="15" qs="0"/>

      <zi han_zi="得" pin_yin="de" sheng_diao="0" id="2635" mistakes="0" times="0" xu_hao="16" qs="0"/>

      <zi han_zi="大" pin_yin="da" sheng_diao="4" id="430" mistakes="0" times="0" xu_hao="17" qs="0"/>

      <zi han_zi="笑" pin_yin="xiao" sheng_diao="4" id="101" mistakes="0" times="0" xu_hao="18" qs="0"/>

      <zi han_zi="起" pin_yin="qi" sheng_diao="3" id="503" mistakes="0" times="0" xu_hao="19" qs="0"/>

      <zi han_zi="来" pin_yin="lai" sheng_diao="2" id="1003" mistakes="0" times="0" xu_hao="20" qs="0"/>

      <zi han_zi="。" pin_yin="" sheng_diao="" id="" mistakes="0" times="0" xu_hao="21" qs="0"/>

    </paragraph>

  </page>

  <page background="" audio_file="" style="10" align="left" line_spacing="25" scale="1.5" position_y="-16" position_x="3" characters_per_row="9" halign="center" valign="middle" rows_per_page="10" gameParagraph="8,10">

    <cue_points>
1143.17,1472.08,1732.80,2045.87,2370.57,2651.35,2799.76,2944.16,4319.97,4624.81,5029.93,5338.79,5651.66,5960.51,6630.37,6915.76,7232.64,7561.55</cue_points>

    <paragraph align="left" style="0">

      <zi han_zi="笑" pin_yin="xiao" sheng_diao="4" id="101" mistakes="0" times="0" xu_hao="0" qs="0"/>

      <zi han_zi="过" pin_yin="guo" sheng_diao="4" id="1882" mistakes="0" times="0" xu_hao="1" qs="0"/>

      <zi han_zi="一" pin_yin="yi" sheng_diao="2" id="2197" mistakes="0" times="0" xu_hao="2" qs="0"/>

      <zi han_zi="阵" pin_yin="zhen" sheng_diao="4" id="2587" mistakes="0" times="0" xu_hao="3" qs="0"/>

      <zi han_zi="后" pin_yin="hou" sheng_diao="4" id="855" mistakes="0" times="0" xu_hao="4" qs="0"/>

      <zi han_zi="他" pin_yin="ta" sheng_diao="1" id="2179" mistakes="0" times="0" xu_hao="5" qs="0"/>

      <zi han_zi="才" pin_yin="cai" sheng_diao="2" id="345" mistakes="0" times="0" xu_hao="6" qs="0"/>

      <zi han_zi="说" pin_yin="shuo" sheng_diao="1" id="2037" mistakes="0" times="0" xu_hao="7" qs="0"/>

      <zi han_zi="：" pin_yin="" sheng_diao="" id="" mistakes="0" times="0" xu_hao="8" qs="0"/>

      <zi han_zi="“" pin_yin="" sheng_diao="" id="" mistakes="0" times="0" xu_hao="9" qs="0"/>

      <zi han_zi="此" pin_yin="ci" sheng_diao="3" id="502" mistakes="0" times="0" xu_hao="10" qs="0"/>

      <zi han_zi="鸟" pin_yin="niao" sheng_diao="3" id="2201" mistakes="0" times="0" xu_hao="11" qs="0"/>

      <zi han_zi="不" pin_yin="bu" sheng_diao="4" id="86" mistakes="0" times="0" xu_hao="12" qs="0"/>

      <zi han_zi="飞" pin_yin="fei" sheng_diao="1" id="415" mistakes="0" times="0" xu_hao="13" qs="0"/>

      <zi han_zi="则" pin_yin="ze" sheng_diao="2" id="2024" mistakes="0" times="0" xu_hao="14" qs="0"/>

      <zi han_zi="已" pin_yin="yi" sheng_diao="3" id="1472" mistakes="0" times="0" xu_hao="15" qs="0"/>

      <zi han_zi="，" pin_yin="" sheng_diao="" id="" mistakes="0" times="0" xu_hao="16" qs="0"/>

      <zi han_zi="一" pin_yin="yi" sheng_diao="4" id="2089" mistakes="0" times="0" xu_hao="17" qs="0"/>

      <zi han_zi="飞" pin_yin="fei" sheng_diao="1" id="415" mistakes="0" times="0" xu_hao="18" qs="0"/>

      <zi han_zi="冲" pin_yin="chong" sheng_diao="1" id="307" mistakes="0" times="0" xu_hao="19" qs="0"/>

      <zi han_zi="天" pin_yin="tian" sheng_diao="1" id="325" mistakes="0" times="0" xu_hao="20" qs="0"/>

      <zi han_zi="。" pin_yin="" sheng_diao="" id="" mistakes="0" times="0" xu_hao="21" qs="0"/>

      <zi han_zi="”" pin_yin="" sheng_diao="" id="" mistakes="0" times="0" xu_hao="22" qs="0"/>

    </paragraph>

  </page>

  <page background="" audio_file="" style="10" align="left" line_spacing="50" scale="2" position_y="-16" position_x="3" characters_per_row="6" halign="center" valign="middle" rows_per_page="10" gameParagraph="">

    <cue_points>
348.27,684.45,1032.52,1253.77,1765.93,2065.04,2351.85,2691.92</cue_points>

    <paragraph align="left" style="0">

      <zi han_zi="“" pin_yin="" sheng_diao="" id="" mistakes="0" times="0" xu_hao="0" qs="0"/>

      <zi han_zi="不" pin_yin="bu" sheng_diao="4" id="86" mistakes="0" times="0" xu_hao="1" qs="0"/>

      <zi han_zi="鸣" pin_yin="ming" sheng_diao="2" id="262" mistakes="0" times="0" xu_hao="2" qs="0"/>

      <zi han_zi="则" pin_yin="ze" sheng_diao="2" id="2024" mistakes="0" times="0" xu_hao="3" qs="0"/>

      <zi han_zi="已" pin_yin="yi" sheng_diao="3" id="1472" mistakes="0" times="0" xu_hao="4" qs="0"/>

      <zi han_zi="，" pin_yin="" sheng_diao="" id="" mistakes="0" times="0" xu_hao="5" qs="0"/>

      <zi han_zi="一" pin_yin="yi" sheng_diao="4" id="2089" mistakes="0" times="0" xu_hao="6" qs="0"/>

      <zi han_zi="鸣" pin_yin="ming" sheng_diao="2" id="262" mistakes="0" times="0" xu_hao="7" qs="0"/>

      <zi han_zi="惊" pin_yin="jing" sheng_diao="1" id="870" mistakes="0" times="0" xu_hao="8" qs="0"/>

      <zi han_zi="人" pin_yin="ren" sheng_diao="2" id="649" mistakes="0" times="0" xu_hao="9" qs="0"/>

      <zi han_zi="。" pin_yin="" sheng_diao="" id="" mistakes="0" times="0" xu_hao="10" qs="0"/>

      <zi han_zi="”" pin_yin="" sheng_diao="" id="" mistakes="0" times="0" xu_hao="11" qs="0"/>

    </paragraph>

  </page>

  <page background="" audio_file="" style="16" align="left" line_spacing="50" scale="1.8" position_y="-16" position_x="3" characters_per_row="8" halign="center" valign="middle" rows_per_page="10" gameParagraph="">

    <cue_points>
1181.14,1489.27,1690.93,1990.96,2970.63,3243.20,3460.47,3839.70,4104.37,4388.79,4661.37,4827.28,5076.15,5351.09</cue_points>

    <paragraph align="left" style="0">

      <zi han_zi="从" pin_yin="cong" sheng_diao="2" id="752" mistakes="0" times="0" xu_hao="0" qs="0"/>

      <zi han_zi="那" pin_yin="na" sheng_diao="4" id="2177" mistakes="0" times="0" xu_hao="1" qs="0"/>

      <zi han_zi="天" pin_yin="tian" sheng_diao="1" id="325" mistakes="0" times="0" xu_hao="2" qs="0"/>

      <zi han_zi="起" pin_yin="qi" sheng_diao="3" id="503" mistakes="0" times="0" xu_hao="3" qs="0"/>

      <zi han_zi="，" pin_yin="" sheng_diao="" id="" mistakes="0" times="0" xu_hao="4" qs="0"/>

      <zi han_zi="齐" pin_yin="qi" sheng_diao="2" id="2038" mistakes="0" times="0" xu_hao="5" qs="0"/>

      <zi han_zi="威" pin_yin="wei" sheng_diao="1" id="2373" mistakes="0" times="0" xu_hao="6" qs="0"/>

      <zi han_zi="王" pin_yin="wang" sheng_diao="2" id="1725" mistakes="0" times="0" xu_hao="7" qs="0"/>

      <zi han_zi="就" pin_yin="jiu" sheng_diao="4" id="2528" mistakes="0" times="0" xu_hao="8" qs="0"/>

      <zi han_zi="到" pin_yin="dao" sheng_diao="4" id="111" mistakes="0" times="0" xu_hao="9" qs="0"/>

      <zi han_zi="各" pin_yin="ge" sheng_diao="4" id="117" mistakes="0" times="0" xu_hao="10" qs="0"/>

      <zi han_zi="地" pin_yin="di" sheng_diao="4" id="1594" mistakes="0" times="0" xu_hao="11" qs="0"/>

      <zi han_zi="去" pin_yin="qv" sheng_diao="4" id="387" mistakes="0" times="0" xu_hao="12" qs="0"/>

      <zi han_zi="视" pin_yin="shi" sheng_diao="4" id="1033" mistakes="0" times="0" xu_hao="13" qs="0"/>

      <zi han_zi="察" pin_yin="cha" sheng_diao="2" id="839" mistakes="0" times="0" xu_hao="14" qs="0"/>

      <zi han_zi="。" pin_yin="" sheng_diao="" id="" mistakes="0" times="0" xu_hao="15" qs="0"/>

    </paragraph>

  </page>

  <page background="" audio_file="" style="16" align="left" line_spacing="50" scale="2" position_y="-16" position_x="3" characters_per_row="7" halign="center" valign="middle" rows_per_page="10" gameParagraph="">

    <cue_points>
570.67,847.86,1149.50,1410.38,1712.02,1907.68,2197.29,2861.51,3243.25,3467.44,3703.87,3960.67</cue_points>

    <paragraph align="left" style="0">

      <zi han_zi="看" pin_yin="kan" sheng_diao="4" id="43" mistakes="0" times="0" xu_hao="0" qs="0"/>

      <zi han_zi="到" pin_yin="dao" sheng_diao="4" id="111" mistakes="0" times="0" xu_hao="1" qs="0"/>

      <zi han_zi="称" pin_yin="chen" sheng_diao="4" id="2588" mistakes="0" times="0" xu_hao="2" qs="0"/>

      <zi han_zi="职" pin_yin="zhi" sheng_diao="2" id="112" mistakes="0" times="0" xu_hao="3" qs="0"/>

      <zi han_zi="的" pin_yin="de" sheng_diao="0" id="2626" mistakes="0" times="0" xu_hao="4" qs="0"/>

      <zi han_zi="大" pin_yin="da" sheng_diao="4" id="430" mistakes="0" times="0" xu_hao="5" qs="0"/>

      <zi han_zi="夫" pin_yin="fu" sheng_diao="1" id="1835" mistakes="0" times="0" xu_hao="6" qs="0"/>

      <zi han_zi="，" pin_yin="" sheng_diao="" id="" mistakes="0" times="0" xu_hao="7" qs="0"/>

      <zi han_zi="就" pin_yin="jiu" sheng_diao="4" id="2528" mistakes="0" times="0" xu_hao="8" qs="0"/>

      <zi han_zi="给" pin_yin="ji" sheng_diao="3" id="1474" mistakes="0" times="0" xu_hao="9" qs="0"/>

      <zi han_zi="予" pin_yin="yv" sheng_diao="3" id="1245" mistakes="0" times="0" xu_hao="10" qs="0"/>

      <zi han_zi="奖" pin_yin="jiang" sheng_diao="3" id="2589" mistakes="0" times="0" xu_hao="11" qs="0"/>

      <zi han_zi="励" pin_yin="li" sheng_diao="4" id="328" mistakes="0" times="0" xu_hao="12" qs="0"/>

      <zi han_zi="。" pin_yin="" sheng_diao="" id="" mistakes="0" times="0" xu_hao="13" qs="0"/>

    </paragraph>

  </page>

  <page background="" audio_file="" style="16" align="left" line_spacing="50" scale="1.6" position_y="-16" position_x="3" characters_per_row="9" halign="center" valign="middle" rows_per_page="10" gameParagraph="8,8">

    <cue_points>
537.54,707.52,945.07,1178.09,1537.00,1771.88,2039.72,2357.01,3249.75,3571.16,3764.83,4028.55,4308.75,4527.15,4733.39,4914.49</cue_points>

    <paragraph align="left" style="0">

      <zi han_zi="他" pin_yin="ta" sheng_diao="1" id="2179" mistakes="0" times="0" xu_hao="0" qs="0"/>

      <zi han_zi="又" pin_yin="you" sheng_diao="4" id="1636" mistakes="0" times="0" xu_hao="1" qs="0"/>

      <zi han_zi="严" pin_yin="yan" sheng_diao="2" id="1031" mistakes="0" times="0" xu_hao="2" qs="0"/>

      <zi han_zi="格" pin_yin="ge" sheng_diao="2" id="1292" mistakes="0" times="0" xu_hao="3" qs="0"/>

      <zi han_zi="整" pin_yin="zheng" sheng_diao="3" id="554" mistakes="0" times="0" xu_hao="4" qs="0"/>

      <zi han_zi="顿" pin_yin="dun" sheng_diao="4" id="2461" mistakes="0" times="0" xu_hao="5" qs="0"/>

      <zi han_zi="军" pin_yin="jvn" sheng_diao="1" id="368" mistakes="0" times="0" xu_hao="6" qs="0"/>

      <zi han_zi="队" pin_yin="dui" sheng_diao="4" id="363" mistakes="0" times="0" xu_hao="7" qs="0"/>

      <zi han_zi="，" pin_yin="" sheng_diao="" id="" mistakes="0" times="0" xu_hao="8" qs="0"/>

      <zi han_zi="打" pin_yin="da" sheng_diao="3" id="546" mistakes="0" times="0" xu_hao="9" qs="0"/>

      <zi han_zi="败" pin_yin="bai" sheng_diao="4" id="1260" mistakes="0" times="0" xu_hao="10" qs="0"/>

      <zi han_zi="了" pin_yin="le" sheng_diao="0" id="50" mistakes="0" times="0" xu_hao="11" qs="0"/>

      <zi han_zi="魏" pin_yin="wei" sheng_diao="4" id="2081" mistakes="0" times="0" xu_hao="12" qs="0"/>

      <zi han_zi="国" pin_yin="guo" sheng_diao="2" id="320" mistakes="0" times="0" xu_hao="13" qs="0"/>

      <zi han_zi="的" pin_yin="de" sheng_diao="0" id="2626" mistakes="0" times="0" xu_hao="14" qs="0"/>

      <zi han_zi="入" pin_yin="ru" sheng_diao="4" id="852" mistakes="0" times="0" xu_hao="15" qs="0"/>

      <zi han_zi="侵" pin_yin="qin" sheng_diao="1" id="1311" mistakes="0" times="0" xu_hao="16" qs="0"/>

      <zi han_zi="。" pin_yin="" sheng_diao="" id="" mistakes="0" times="0" xu_hao="17" qs="0"/>

    </paragraph>

  </page>

  <page background="" audio_file="" style="16" align="left" line_spacing="15" scale="1.6" position_y="-16" position_x="3" characters_per_row="8" halign="center" valign="middle" rows_per_page="10" gameParagraph="7,10">

    <cue_points>
438.66,819.39,1084.24,1398.75,1738.10,2056.75,2362.98,3207.20,3563.10,3848.64,4109.36,4374.21,4928.74,5197.94,5441.90,5727.44,6020.02</cue_points>

    <paragraph align="left" style="0">

      <zi han_zi="齐" pin_yin="qi" sheng_diao="2" id="2038" mistakes="0" times="0" xu_hao="0" qs="0"/>

      <zi han_zi="威" pin_yin="wei" sheng_diao="1" id="2373" mistakes="0" times="0" xu_hao="1" qs="0"/>

      <zi han_zi="王" pin_yin="wang" sheng_diao="2" id="1725" mistakes="0" times="0" xu_hao="2" qs="0"/>

      <zi han_zi="一" pin_yin="yi" sheng_diao="4" id="2089" mistakes="0" times="0" xu_hao="3" qs="0"/>

      <zi han_zi="鸣" pin_yin="ming" sheng_diao="2" id="262" mistakes="0" times="0" xu_hao="4" qs="0"/>

      <zi han_zi="惊" pin_yin="jing" sheng_diao="1" id="870" mistakes="0" times="0" xu_hao="5" qs="0"/>

      <zi han_zi="人" pin_yin="ren" sheng_diao="2" id="649" mistakes="0" times="0" xu_hao="6" qs="0"/>

      <zi han_zi="，" pin_yin="" sheng_diao="" id="" mistakes="0" times="0" xu_hao="7" qs="0"/>

      <zi han_zi="使" pin_yin="shi" sheng_diao="3" id="1810" mistakes="0" times="0" xu_hao="8" qs="0"/>

      <zi han_zi="各" pin_yin="ge" sheng_diao="4" id="117" mistakes="0" times="0" xu_hao="9" qs="0"/>

      <zi han_zi="国" pin_yin="guo" sheng_diao="2" id="320" mistakes="0" times="0" xu_hao="10" qs="0"/>

      <zi han_zi="君" pin_yin="jvn" sheng_diao="1" id="1724" mistakes="0" times="0" xu_hao="11" qs="0"/>

      <zi han_zi="主" pin_yin="zhu" sheng_diao="3" id="651" mistakes="0" times="0" xu_hao="12" qs="0"/>

      <zi han_zi="都" pin_yin="dou" sheng_diao="1" id="121" mistakes="0" times="0" xu_hao="13" qs="0"/>

      <zi han_zi="感" pin_yin="gan" sheng_diao="3" id="810" mistakes="0" times="0" xu_hao="14" qs="0"/>

      <zi han_zi="到" pin_yin="dao" sheng_diao="4" id="111" mistakes="0" times="0" xu_hao="15" qs="0"/>

      <zi han_zi="震" pin_yin="zhen" sheng_diao="4" id="2533" mistakes="0" times="0" xu_hao="16" qs="0"/>

      <zi han_zi="惊" pin_yin="jing" sheng_diao="1" id="870" mistakes="0" times="0" xu_hao="17" qs="0"/>

      <zi han_zi="。" pin_yin="" sheng_diao="" id="" mistakes="0" times="0" xu_hao="18" qs="0"/>

    </paragraph>

  </page>

  <page background="" audio_file="" style="19" align="left" line_spacing="15" scale="1.6" position_y="-16" position_x="3" characters_per_row="9" halign="center" valign="middle" rows_per_page="10" gameParagraph="6,8,9">

    <cue_points>
460.01,861.99,1591.58,1927.05,2179.85,2478.23,3307.07,3526.71,3775.57,4024.23,4434.29,4683.15,4923.31,5209.26,6108.55,6270.17,6547.84,6796.69,7144.60,7393.46,7592.17,7741.37,7990.22</cue_points>

    <paragraph align="left" style="0">

      <zi han_zi="成" pin_yin="cheng" sheng_diao="2" id="1442" mistakes="0" times="0" xu_hao="0" qs="0"/>

      <zi han_zi="语" pin_yin="yv" sheng_diao="3" id="2747" mistakes="0" times="0" xu_hao="1" qs="0"/>

      <zi han_zi="一" pin_yin="yi" sheng_diao="4" id="2089" mistakes="0" times="0" xu_hao="2" qs="0"/>

      <zi han_zi="鸣" pin_yin="ming" sheng_diao="2" id="262" mistakes="0" times="0" xu_hao="3" qs="0"/>

      <zi han_zi="惊" pin_yin="jing" sheng_diao="1" id="870" mistakes="0" times="0" xu_hao="4" qs="0"/>

      <zi han_zi="人" pin_yin="ren" sheng_diao="2" id="649" mistakes="0" times="0" xu_hao="5" qs="0"/>

      <zi han_zi="比" pin_yin="bi" sheng_diao="3" id="2289" mistakes="0" times="0" xu_hao="6" qs="0"/>

      <zi han_zi="喻" pin_yin="yv" sheng_diao="4" id="2586" mistakes="0" times="0" xu_hao="7" qs="0"/>

      <zi han_zi="平" pin_yin="ping" sheng_diao="2" id="404" mistakes="0" times="0" xu_hao="8" qs="0"/>

      <zi han_zi="时" pin_yin="shi" sheng_diao="2" id="1523" mistakes="0" times="0" xu_hao="9" qs="0"/>

      <zi han_zi="默" pin_yin="mo" sheng_diao="4" id="2415" mistakes="0" times="0" xu_hao="10" qs="0"/>

      <zi han_zi="默" pin_yin="mo" sheng_diao="4" id="2415" mistakes="0" times="0" xu_hao="11" qs="0"/>

      <zi han_zi="无" pin_yin="wu" sheng_diao="2" id="68" mistakes="0" times="0" xu_hao="12" qs="0"/>

      <zi han_zi="闻" pin_yin="wen" sheng_diao="2" id="1996" mistakes="0" times="0" xu_hao="13" qs="0"/>

      <zi han_zi="，" pin_yin="" sheng_diao="" id="" mistakes="0" times="0" xu_hao="14" qs="0"/>

      <zi han_zi="突" pin_yin="tu" sheng_diao="1" id="461" mistakes="0" times="0" xu_hao="15" qs="0"/>

      <zi han_zi="然" pin_yin="ran" sheng_diao="2" id="1690" mistakes="0" times="0" xu_hao="16" qs="0"/>

      <zi han_zi="干" pin_yin="gan" sheng_diao="4" id="2762" mistakes="0" times="0" xu_hao="17" qs="0"/>

      <zi han_zi="出" pin_yin="chu" sheng_diao="1" id="544" mistakes="0" times="0" xu_hao="18" qs="0"/>

      <zi han_zi="惊" pin_yin="jing" sheng_diao="1" id="870" mistakes="0" times="0" xu_hao="19" qs="0"/>

      <zi han_zi="人" pin_yin="ren" sheng_diao="2" id="649" mistakes="0" times="0" xu_hao="20" qs="0"/>

      <zi han_zi="的" pin_yin="de" sheng_diao="0" id="2626" mistakes="0" times="0" xu_hao="21" qs="0"/>

      <zi han_zi="事" pin_yin="shi" sheng_diao="4" id="620" mistakes="0" times="0" xu_hao="22" qs="0"/>

      <zi han_zi="来" pin_yin="lai" sheng_diao="2" id="1003" mistakes="0" times="0" xu_hao="23" qs="1"/>

      <zi han_zi="。" pin_yin="" sheng_diao="" id="" mistakes="0" times="0" xu_hao="24" qs="0"/>

      <zi han_zi="" pin_yin="" sheng_diao="" mistakes="0" times="0" xu_hao="25" qs="0"/>

      <zi han_zi="" pin_yin="" sheng_diao="" mistakes="0" times="0" xu_hao="26" qs="0"/>

    </paragraph>

  </page>

</pages>

