<pages has_audio="1" background="default.jpg" scale="1.3" valign="middle" halign="center" line_spacing="5" characters_per_row="8" rows_per_page="10" position_x="-5" position_y="45" style="1">

  <page background="" audio_file="" style="1" align="left" line_spacing="3" scale="1.3" position_y="-16" position_x="3" characters_per_row="8" rows_per_page="10" halign="center" valign="middle" gameParagraph="7,7,7,7">

    <cue_points>
29410.49,29864.68,30363.93,30773.68,32487.55,33565.19,34120.45,35708.30,36188.67,36629.47,37084.27,39250.52,40001.82,40408.52,42122.40,42695.92,43136.72,43515.42,45225.64,46212.57,46770.87,48784.30,49108.20,49471.67,49926.47,51743.25,52671.11,53034.59</cue_points>

    <paragraph align="left" style="0">

      <zi han_zi="清" pin_yin="qing" sheng_diao="1" id="336" mistakes="0" times="0" xu_hao="0" qs="0"/>

      <zi han_zi="明" pin_yin="ming" sheng_diao="2" id="55" mistakes="0" times="0" xu_hao="1" qs="0"/>

      <zi han_zi="时" pin_yin="shi" sheng_diao="2" id="1523" mistakes="0" times="0" xu_hao="2" qs="0"/>

      <zi han_zi="节" pin_yin="jie" sheng_diao="2" id="" mistakes="0" times="0" xu_hao="3" qs="0"/>

      <zi han_zi="雨" pin_yin="yv" sheng_diao="3" id="232" mistakes="0" times="0" xu_hao="4" qs="0"/>

      <zi han_zi="纷" pin_yin="fen" sheng_diao="1" id="" mistakes="0" times="0" xu_hao="5" qs="0"/>

      <zi han_zi="纷" pin_yin="fen" sheng_diao="1" id="" mistakes="0" times="0" xu_hao="6" qs="0"/>

      <zi han_zi="，" pin_yin="" sheng_diao="" id="" mistakes="0" times="0" xu_hao="7" qs="0"/>

      <zi han_zi="路" pin_yin="lu" sheng_diao="4" id="432" mistakes="0" times="0" xu_hao="8" qs="0"/>

      <zi han_zi="上" pin_yin="shang" sheng_diao="4" id="1226" mistakes="0" times="0" xu_hao="9" qs="0"/>

      <zi han_zi="行" pin_yin="xing" sheng_diao="2" id="96" mistakes="0" times="0" xu_hao="10" qs="0"/>

      <zi han_zi="人" pin_yin="ren" sheng_diao="2" id="649" mistakes="0" times="0" xu_hao="11" qs="0"/>

      <zi han_zi="欲" pin_yin="yv" sheng_diao="4" id="1677" mistakes="0" times="0" xu_hao="12" qs="0"/>

      <zi han_zi="断" pin_yin="duan" sheng_diao="4" id="816" mistakes="0" times="0" xu_hao="13" qs="0"/>

      <zi han_zi="魂" pin_yin="hun" sheng_diao="2" id="648" mistakes="0" times="0" xu_hao="14" qs="0"/>

      <zi han_zi="。" pin_yin="" sheng_diao="" id="" mistakes="0" times="0" xu_hao="15" qs="0"/>

      <zi han_zi="借" pin_yin="jie" sheng_diao="4" id="439" mistakes="0" times="0" xu_hao="16" qs="0"/>

      <zi han_zi="问" pin_yin="wen" sheng_diao="4" id="126" mistakes="0" times="0" xu_hao="17" qs="0"/>

      <zi han_zi="酒" pin_yin="jiu" sheng_diao="3" id="965" mistakes="0" times="0" xu_hao="18" qs="0"/>

      <zi han_zi="家" pin_yin="jia" sheng_diao="1" id="1858" mistakes="0" times="0" xu_hao="19" qs="0"/>

      <zi han_zi="何" pin_yin="he" sheng_diao="2" id="1522" mistakes="0" times="0" xu_hao="20" qs="0"/>

      <zi han_zi="处" pin_yin="chu" sheng_diao="4" id="1979" mistakes="0" times="0" xu_hao="21" qs="0"/>

      <zi han_zi="有" pin_yin="you" sheng_diao="3" id="282" mistakes="0" times="0" xu_hao="22" qs="0"/>

      <zi han_zi="？" pin_yin="" sheng_diao="" id="" mistakes="0" times="0" xu_hao="23" qs="0"/>

      <zi han_zi="牧" pin_yin="mu" sheng_diao="4" id="894" mistakes="0" times="0" xu_hao="24" qs="0"/>

      <zi han_zi="童" pin_yin="tong" sheng_diao="2" id="908" mistakes="0" times="0" xu_hao="25" qs="0"/>

      <zi han_zi="遥" pin_yin="yao" sheng_diao="2" id="446" mistakes="0" times="0" xu_hao="26" qs="0"/>

      <zi han_zi="指" pin_yin="zhi" sheng_diao="3" id="" mistakes="0" times="0" xu_hao="27" qs="0"/>

      <zi han_zi="杏" pin_yin="xing" sheng_diao="4" id="" mistakes="0" times="0" xu_hao="28" qs="0"/>

      <zi han_zi="花" pin_yin="hua" sheng_diao="1" id="147" mistakes="0" times="0" xu_hao="29" qs="0"/>

      <zi han_zi="村" pin_yin="cun" sheng_diao="1" id="1638" mistakes="0" times="0" xu_hao="30" qs="0"/>

      <zi han_zi="。" pin_yin="" sheng_diao="" id="" mistakes="0" times="0" xu_hao="31" qs="0"/>

    </paragraph>

  </page>

  <page background="" audio_file="" style="2" align="left" line_spacing="3" scale="1.3" position_y="-16" position_x="3" characters_per_row="8" rows_per_page="10" halign="center" valign="middle" gameParagraph="7,7,7,7">

    <cue_points>
828.29,1215.64,1590.81,2054.49,2436.15,2850.30,3321.29,4117.10,4360.71,4718.02,5221.49,5790.33,6135.86,6543.51,7235.38,7746.97,8023.47,8510.30,8924.44,9200.95,9647.17,10434.86,10849.00,11181.94,11693.54,11993.99,12976.58,13691.18</cue_points>

    <paragraph align="left" style="0">

      <zi han_zi="清" pin_yin="qing" sheng_diao="1" id="336" mistakes="0" times="0" xu_hao="0" qs="0"/>

      <zi han_zi="明" pin_yin="ming" sheng_diao="2" id="55" mistakes="0" times="0" xu_hao="1" qs="0"/>

      <zi han_zi="时" pin_yin="shi" sheng_diao="2" id="1523" mistakes="0" times="0" xu_hao="2" qs="0"/>

      <zi han_zi="节" pin_yin="jie" sheng_diao="2" id="" mistakes="0" times="0" xu_hao="3" qs="0"/>

      <zi han_zi="雨" pin_yin="yv" sheng_diao="3" id="232" mistakes="0" times="0" xu_hao="4" qs="0"/>

      <zi han_zi="纷" pin_yin="fen" sheng_diao="1" id="" mistakes="0" times="0" xu_hao="5" qs="0"/>

      <zi han_zi="纷" pin_yin="fen" sheng_diao="1" id="" mistakes="0" times="0" xu_hao="6" qs="0"/>

      <zi han_zi="，" pin_yin="" sheng_diao="" id="" mistakes="0" times="0" xu_hao="7" qs="0"/>

      <zi han_zi="路" pin_yin="lu" sheng_diao="4" id="432" mistakes="0" times="0" xu_hao="8" qs="0"/>

      <zi han_zi="上" pin_yin="shang" sheng_diao="4" id="1226" mistakes="0" times="0" xu_hao="9" qs="0"/>

      <zi han_zi="行" pin_yin="xing" sheng_diao="2" id="96" mistakes="0" times="0" xu_hao="10" qs="0"/>

      <zi han_zi="人" pin_yin="ren" sheng_diao="2" id="649" mistakes="0" times="0" xu_hao="11" qs="0"/>

      <zi han_zi="欲" pin_yin="yv" sheng_diao="4" id="1677" mistakes="0" times="0" xu_hao="12" qs="0"/>

      <zi han_zi="断" pin_yin="duan" sheng_diao="4" id="816" mistakes="0" times="0" xu_hao="13" qs="0"/>

      <zi han_zi="魂" pin_yin="hun" sheng_diao="2" id="648" mistakes="0" times="0" xu_hao="14" qs="0"/>

      <zi han_zi="。" pin_yin="" sheng_diao="" id="" mistakes="0" times="0" xu_hao="15" qs="0"/>

      <zi han_zi="借" pin_yin="jie" sheng_diao="4" id="439" mistakes="0" times="0" xu_hao="16" qs="0"/>

      <zi han_zi="问" pin_yin="wen" sheng_diao="4" id="126" mistakes="0" times="0" xu_hao="17" qs="0"/>

      <zi han_zi="酒" pin_yin="jiu" sheng_diao="3" id="965" mistakes="0" times="0" xu_hao="18" qs="0"/>

      <zi han_zi="家" pin_yin="jia" sheng_diao="1" id="1858" mistakes="0" times="0" xu_hao="19" qs="0"/>

      <zi han_zi="何" pin_yin="he" sheng_diao="2" id="1522" mistakes="0" times="0" xu_hao="20" qs="0"/>

      <zi han_zi="处" pin_yin="chu" sheng_diao="4" id="1979" mistakes="0" times="0" xu_hao="21" qs="0"/>

      <zi han_zi="有" pin_yin="you" sheng_diao="3" id="282" mistakes="0" times="0" xu_hao="22" qs="0"/>

      <zi han_zi="？" pin_yin="" sheng_diao="" id="" mistakes="0" times="0" xu_hao="23" qs="0"/>

      <zi han_zi="牧" pin_yin="mu" sheng_diao="4" id="894" mistakes="0" times="0" xu_hao="24" qs="0"/>

      <zi han_zi="童" pin_yin="tong" sheng_diao="2" id="908" mistakes="0" times="0" xu_hao="25" qs="0"/>

      <zi han_zi="遥" pin_yin="yao" sheng_diao="2" id="446" mistakes="0" times="0" xu_hao="26" qs="0"/>

      <zi han_zi="指" pin_yin="zhi" sheng_diao="3" id="" mistakes="0" times="0" xu_hao="27" qs="0"/>

      <zi han_zi="杏" pin_yin="xing" sheng_diao="4" id="" mistakes="0" times="0" xu_hao="28" qs="0"/>

      <zi han_zi="花" pin_yin="hua" sheng_diao="1" id="147" mistakes="0" times="0" xu_hao="29" qs="0"/>

      <zi han_zi="村" pin_yin="cun" sheng_diao="1" id="1638" mistakes="0" times="0" xu_hao="30" qs="0"/>

      <zi han_zi="。" pin_yin="" sheng_diao="" id="" mistakes="0" times="0" xu_hao="31" qs="0"/>

    </paragraph>

  </page>

  <page background="" audio_file="" style="3" align="left" line_spacing="3" scale="1.3" position_y="-16" position_x="3" characters_per_row="8" rows_per_page="10" halign="center" valign="middle" gameParagraph="7,7,7,7">

    <cue_points>
488.65,1043.56,1325.16,1888.35,3967.19,4571.79,4987.97,6832.84,7329.77,7727.32,8199.82,10353.20,11073.76,11362.39,13425.91,13906.28,14234.26,14551.88,16896.16,17305.72,17955.88,19786.25,20210.71,20539.93,21003.74,21285.33,22221.23,23066.01</cue_points>

    <paragraph align="left" style="0">

      <zi han_zi="清" pin_yin="qing" sheng_diao="1" id="336" mistakes="0" times="0" xu_hao="0" qs="0"/>

      <zi han_zi="明" pin_yin="ming" sheng_diao="2" id="55" mistakes="0" times="0" xu_hao="1" qs="0"/>

      <zi han_zi="时" pin_yin="shi" sheng_diao="2" id="1523" mistakes="0" times="0" xu_hao="2" qs="0"/>

      <zi han_zi="节" pin_yin="jie" sheng_diao="2" id="" mistakes="0" times="0" xu_hao="3" qs="0"/>

      <zi han_zi="雨" pin_yin="yv" sheng_diao="3" id="232" mistakes="0" times="0" xu_hao="4" qs="0"/>

      <zi han_zi="纷" pin_yin="fen" sheng_diao="1" id="" mistakes="0" times="0" xu_hao="5" qs="0"/>

      <zi han_zi="纷" pin_yin="fen" sheng_diao="1" id="" mistakes="0" times="0" xu_hao="6" qs="0"/>

      <zi han_zi="，" pin_yin="" sheng_diao="" id="" mistakes="0" times="0" xu_hao="7" qs="0"/>

      <zi han_zi="路" pin_yin="lu" sheng_diao="4" id="432" mistakes="0" times="0" xu_hao="8" qs="0"/>

      <zi han_zi="上" pin_yin="shang" sheng_diao="4" id="1226" mistakes="0" times="0" xu_hao="9" qs="0"/>

      <zi han_zi="行" pin_yin="xing" sheng_diao="2" id="96" mistakes="0" times="0" xu_hao="10" qs="0"/>

      <zi han_zi="人" pin_yin="ren" sheng_diao="2" id="649" mistakes="0" times="0" xu_hao="11" qs="0"/>

      <zi han_zi="欲" pin_yin="yv" sheng_diao="4" id="1677" mistakes="0" times="0" xu_hao="12" qs="0"/>

      <zi han_zi="断" pin_yin="duan" sheng_diao="4" id="816" mistakes="0" times="0" xu_hao="13" qs="0"/>

      <zi han_zi="魂" pin_yin="hun" sheng_diao="2" id="648" mistakes="0" times="0" xu_hao="14" qs="0"/>

      <zi han_zi="。" pin_yin="" sheng_diao="" id="" mistakes="0" times="0" xu_hao="15" qs="0"/>

      <zi han_zi="借" pin_yin="jie" sheng_diao="4" id="439" mistakes="0" times="0" xu_hao="16" qs="0"/>

      <zi han_zi="问" pin_yin="wen" sheng_diao="4" id="126" mistakes="0" times="0" xu_hao="17" qs="0"/>

      <zi han_zi="酒" pin_yin="jiu" sheng_diao="3" id="965" mistakes="0" times="0" xu_hao="18" qs="0"/>

      <zi han_zi="家" pin_yin="jia" sheng_diao="1" id="1858" mistakes="0" times="0" xu_hao="19" qs="0"/>

      <zi han_zi="何" pin_yin="he" sheng_diao="2" id="1522" mistakes="0" times="0" xu_hao="20" qs="0"/>

      <zi han_zi="处" pin_yin="chu" sheng_diao="4" id="1979" mistakes="0" times="0" xu_hao="21" qs="0"/>

      <zi han_zi="有" pin_yin="you" sheng_diao="3" id="282" mistakes="0" times="0" xu_hao="22" qs="0"/>

      <zi han_zi="？" pin_yin="" sheng_diao="" id="" mistakes="0" times="0" xu_hao="23" qs="0"/>

      <zi han_zi="牧" pin_yin="mu" sheng_diao="4" id="894" mistakes="0" times="0" xu_hao="24" qs="0"/>

      <zi han_zi="童" pin_yin="tong" sheng_diao="2" id="908" mistakes="0" times="0" xu_hao="25" qs="0"/>

      <zi han_zi="遥" pin_yin="yao" sheng_diao="2" id="446" mistakes="0" times="0" xu_hao="26" qs="0"/>

      <zi han_zi="指" pin_yin="zhi" sheng_diao="3" id="" mistakes="0" times="0" xu_hao="27" qs="0"/>

      <zi han_zi="杏" pin_yin="xing" sheng_diao="4" id="" mistakes="0" times="0" xu_hao="28" qs="0"/>

      <zi han_zi="花" pin_yin="hua" sheng_diao="1" id="147" mistakes="0" times="0" xu_hao="29" qs="0"/>

      <zi han_zi="村" pin_yin="cun" sheng_diao="1" id="1638" mistakes="0" times="0" xu_hao="30" qs="0"/>

      <zi han_zi="。" pin_yin="" sheng_diao="" id="" mistakes="0" times="0" xu_hao="31" qs="0"/>

    </paragraph>

  </page>

  <page background="" audio_file="" style="4" align="left" line_spacing="3" scale="1.3" position_y="-16" position_x="3" characters_per_row="8" rows_per_page="10" halign="center" valign="middle" gameParagraph="7,7,7,7">

    <cue_points>
350.24,652.53,1032.02,1589.48,3448.74,4214.63,4770.46,6603.31,7165.64,7524.41,7866.12,9937.47,10630.23,11043.85,13172.90,13554.43,13863.22,14245.15,16344.95,16951.16,17560.62,19605.97,19957.84,20234.12,20616.46,22623.21,23289.56,23907.15</cue_points>

    <paragraph align="left" style="0">

      <zi han_zi="清" pin_yin="qing" sheng_diao="1" id="336" mistakes="0" times="0" xu_hao="0" qs="0"/>

      <zi han_zi="明" pin_yin="ming" sheng_diao="2" id="55" mistakes="0" times="0" xu_hao="1" qs="0"/>

      <zi han_zi="时" pin_yin="shi" sheng_diao="2" id="1523" mistakes="0" times="0" xu_hao="2" qs="0"/>

      <zi han_zi="节" pin_yin="jie" sheng_diao="2" id="" mistakes="0" times="0" xu_hao="3" qs="0"/>

      <zi han_zi="雨" pin_yin="yv" sheng_diao="3" id="232" mistakes="0" times="0" xu_hao="4" qs="0"/>

      <zi han_zi="纷" pin_yin="fen" sheng_diao="1" id="" mistakes="0" times="0" xu_hao="5" qs="0"/>

      <zi han_zi="纷" pin_yin="fen" sheng_diao="1" id="" mistakes="0" times="0" xu_hao="6" qs="0"/>

      <zi han_zi="，" pin_yin="" sheng_diao="" id="" mistakes="0" times="0" xu_hao="7" qs="0"/>

      <zi han_zi="路" pin_yin="lu" sheng_diao="4" id="432" mistakes="0" times="0" xu_hao="8" qs="0"/>

      <zi han_zi="上" pin_yin="shang" sheng_diao="4" id="1226" mistakes="0" times="0" xu_hao="9" qs="0"/>

      <zi han_zi="行" pin_yin="xing" sheng_diao="2" id="96" mistakes="0" times="0" xu_hao="10" qs="0"/>

      <zi han_zi="人" pin_yin="ren" sheng_diao="2" id="649" mistakes="0" times="0" xu_hao="11" qs="0"/>

      <zi han_zi="欲" pin_yin="yv" sheng_diao="4" id="1677" mistakes="0" times="0" xu_hao="12" qs="0"/>

      <zi han_zi="断" pin_yin="duan" sheng_diao="4" id="816" mistakes="0" times="0" xu_hao="13" qs="0"/>

      <zi han_zi="魂" pin_yin="hun" sheng_diao="2" id="648" mistakes="0" times="0" xu_hao="14" qs="0"/>

      <zi han_zi="。" pin_yin="" sheng_diao="" id="" mistakes="0" times="0" xu_hao="15" qs="0"/>

      <zi han_zi="借" pin_yin="jie" sheng_diao="4" id="439" mistakes="0" times="0" xu_hao="16" qs="0"/>

      <zi han_zi="问" pin_yin="wen" sheng_diao="4" id="126" mistakes="0" times="0" xu_hao="17" qs="0"/>

      <zi han_zi="酒" pin_yin="jiu" sheng_diao="3" id="965" mistakes="0" times="0" xu_hao="18" qs="0"/>

      <zi han_zi="家" pin_yin="jia" sheng_diao="1" id="1858" mistakes="0" times="0" xu_hao="19" qs="0"/>

      <zi han_zi="何" pin_yin="he" sheng_diao="2" id="1522" mistakes="0" times="0" xu_hao="20" qs="0"/>

      <zi han_zi="处" pin_yin="chu" sheng_diao="4" id="1979" mistakes="0" times="0" xu_hao="21" qs="0"/>

      <zi han_zi="有" pin_yin="you" sheng_diao="3" id="282" mistakes="0" times="0" xu_hao="22" qs="0"/>

      <zi han_zi="？" pin_yin="" sheng_diao="" id="" mistakes="0" times="0" xu_hao="23" qs="0"/>

      <zi han_zi="牧" pin_yin="mu" sheng_diao="4" id="894" mistakes="0" times="0" xu_hao="24" qs="0"/>

      <zi han_zi="童" pin_yin="tong" sheng_diao="2" id="908" mistakes="0" times="0" xu_hao="25" qs="0"/>

      <zi han_zi="遥" pin_yin="yao" sheng_diao="2" id="446" mistakes="0" times="0" xu_hao="26" qs="0"/>

      <zi han_zi="指" pin_yin="zhi" sheng_diao="3" id="" mistakes="0" times="0" xu_hao="27" qs="0"/>

      <zi han_zi="杏" pin_yin="xing" sheng_diao="4" id="" mistakes="0" times="0" xu_hao="28" qs="0"/>

      <zi han_zi="花" pin_yin="hua" sheng_diao="1" id="147" mistakes="0" times="0" xu_hao="29" qs="0"/>

      <zi han_zi="村" pin_yin="cun" sheng_diao="1" id="1638" mistakes="0" times="0" xu_hao="30" qs="0"/>

      <zi han_zi="。" pin_yin="" sheng_diao="" id="" mistakes="0" times="0" xu_hao="31" qs="0"/>

    </paragraph>

  </page>

  <page background="" audio_file="" style="5" align="left" line_spacing="3" scale="1.3" position_y="-16" position_x="3" characters_per_row="8" rows_per_page="10" halign="center" valign="middle" gameParagraph="7,7,7,7">

    <cue_points>
481.39,1115.23,1468.25,1741.04,2222.44,2623.60,3024.76,3867.20,4228.25,4637.43,5094.76,5463.83,5856.97,6161.85,6795.69,7485.68,7959.06,8488.59,8961.96,9347.08,9603.82,10325.91,10743.12,11272.65,11650.15,12131.54,12869.28,13703.70</cue_points>

    <paragraph align="left" style="0">

      <zi han_zi="清" pin_yin="qing" sheng_diao="1" id="336" mistakes="0" times="0" xu_hao="0" qs="0"/>

      <zi han_zi="明" pin_yin="ming" sheng_diao="2" id="55" mistakes="0" times="0" xu_hao="1" qs="0"/>

      <zi han_zi="时" pin_yin="shi" sheng_diao="2" id="1523" mistakes="0" times="0" xu_hao="2" qs="0"/>

      <zi han_zi="节" pin_yin="jie" sheng_diao="2" id="" mistakes="0" times="0" xu_hao="3" qs="0"/>

      <zi han_zi="雨" pin_yin="yv" sheng_diao="3" id="232" mistakes="0" times="0" xu_hao="4" qs="0"/>

      <zi han_zi="纷" pin_yin="fen" sheng_diao="1" id="" mistakes="0" times="0" xu_hao="5" qs="0"/>

      <zi han_zi="纷" pin_yin="fen" sheng_diao="1" id="" mistakes="0" times="0" xu_hao="6" qs="0"/>

      <zi han_zi="，" pin_yin="" sheng_diao="" id="" mistakes="0" times="0" xu_hao="7" qs="0"/>

      <zi han_zi="路" pin_yin="lu" sheng_diao="4" id="432" mistakes="0" times="0" xu_hao="8" qs="0"/>

      <zi han_zi="上" pin_yin="shang" sheng_diao="4" id="1226" mistakes="0" times="0" xu_hao="9" qs="0"/>

      <zi han_zi="行" pin_yin="xing" sheng_diao="2" id="96" mistakes="0" times="0" xu_hao="10" qs="0"/>

      <zi han_zi="人" pin_yin="ren" sheng_diao="2" id="649" mistakes="0" times="0" xu_hao="11" qs="0"/>

      <zi han_zi="欲" pin_yin="yv" sheng_diao="4" id="1677" mistakes="0" times="0" xu_hao="12" qs="0"/>

      <zi han_zi="断" pin_yin="duan" sheng_diao="4" id="816" mistakes="0" times="0" xu_hao="13" qs="0"/>

      <zi han_zi="魂" pin_yin="hun" sheng_diao="2" id="648" mistakes="0" times="0" xu_hao="14" qs="0"/>

      <zi han_zi="。" pin_yin="" sheng_diao="" id="" mistakes="0" times="0" xu_hao="15" qs="0"/>

      <zi han_zi="借" pin_yin="jie" sheng_diao="4" id="439" mistakes="0" times="0" xu_hao="16" qs="0"/>

      <zi han_zi="问" pin_yin="wen" sheng_diao="4" id="126" mistakes="0" times="0" xu_hao="17" qs="0"/>

      <zi han_zi="酒" pin_yin="jiu" sheng_diao="3" id="965" mistakes="0" times="0" xu_hao="18" qs="0"/>

      <zi han_zi="家" pin_yin="jia" sheng_diao="1" id="1858" mistakes="0" times="0" xu_hao="19" qs="0"/>

      <zi han_zi="何" pin_yin="he" sheng_diao="2" id="1522" mistakes="0" times="0" xu_hao="20" qs="0"/>

      <zi han_zi="处" pin_yin="chu" sheng_diao="4" id="1979" mistakes="0" times="0" xu_hao="21" qs="0"/>

      <zi han_zi="有" pin_yin="you" sheng_diao="3" id="282" mistakes="0" times="0" xu_hao="22" qs="0"/>

      <zi han_zi="？" pin_yin="" sheng_diao="" id="" mistakes="0" times="0" xu_hao="23" qs="0"/>

      <zi han_zi="牧" pin_yin="mu" sheng_diao="4" id="894" mistakes="0" times="0" xu_hao="24" qs="0"/>

      <zi han_zi="童" pin_yin="tong" sheng_diao="2" id="908" mistakes="0" times="0" xu_hao="25" qs="0"/>

      <zi han_zi="遥" pin_yin="yao" sheng_diao="2" id="446" mistakes="0" times="0" xu_hao="26" qs="0"/>

      <zi han_zi="指" pin_yin="zhi" sheng_diao="3" id="" mistakes="0" times="0" xu_hao="27" qs="0"/>

      <zi han_zi="杏" pin_yin="xing" sheng_diao="4" id="" mistakes="0" times="0" xu_hao="28" qs="0"/>

      <zi han_zi="花" pin_yin="hua" sheng_diao="1" id="147" mistakes="0" times="0" xu_hao="29" qs="0"/>

      <zi han_zi="村" pin_yin="cun" sheng_diao="1" id="1638" mistakes="0" times="0" xu_hao="30" qs="0"/>

      <zi han_zi="。" pin_yin="" sheng_diao="" id="" mistakes="0" times="0" xu_hao="31" qs="0"/>

    </paragraph>

  </page>

  <page background="" audio_file="" style="6" align="left" line_spacing="3" scale="1.3" position_y="-16" position_x="3" characters_per_row="8" rows_per_page="10" halign="center" valign="middle" gameParagraph="7,7,7,7">

    <cue_points>
340.70,838.27,1087.27,1718.05,3593.79,4432.47,4813.85,6789.60,7253.97,7619.16,8009.25,10059.28,10731.56,11188.04,13113.58,13561.77,13918.66,14408.76,16732.27,17114.06,17446.05,19421.38,19861.27,20334.35,20707.84,21222.43,23106.47,24368.44</cue_points>

    <paragraph align="left" style="0">

      <zi han_zi="清" pin_yin="qing" sheng_diao="1" id="336" mistakes="0" times="0" xu_hao="0" qs="0"/>

      <zi han_zi="明" pin_yin="ming" sheng_diao="2" id="55" mistakes="0" times="0" xu_hao="1" qs="0"/>

      <zi han_zi="时" pin_yin="shi" sheng_diao="2" id="1523" mistakes="0" times="0" xu_hao="2" qs="0"/>

      <zi han_zi="节" pin_yin="jie" sheng_diao="2" id="" mistakes="0" times="0" xu_hao="3" qs="0"/>

      <zi han_zi="雨" pin_yin="yv" sheng_diao="3" id="232" mistakes="0" times="0" xu_hao="4" qs="0"/>

      <zi han_zi="纷" pin_yin="fen" sheng_diao="1" id="" mistakes="0" times="0" xu_hao="5" qs="0"/>

      <zi han_zi="纷" pin_yin="fen" sheng_diao="1" id="" mistakes="0" times="0" xu_hao="6" qs="0"/>

      <zi han_zi="，" pin_yin="" sheng_diao="" id="" mistakes="0" times="0" xu_hao="7" qs="0"/>

      <zi han_zi="路" pin_yin="lu" sheng_diao="4" id="432" mistakes="0" times="0" xu_hao="8" qs="0"/>

      <zi han_zi="上" pin_yin="shang" sheng_diao="4" id="1226" mistakes="0" times="0" xu_hao="9" qs="0"/>

      <zi han_zi="行" pin_yin="xing" sheng_diao="2" id="96" mistakes="0" times="0" xu_hao="10" qs="0"/>

      <zi han_zi="人" pin_yin="ren" sheng_diao="2" id="649" mistakes="0" times="0" xu_hao="11" qs="0"/>

      <zi han_zi="欲" pin_yin="yv" sheng_diao="4" id="1677" mistakes="0" times="0" xu_hao="12" qs="0"/>

      <zi han_zi="断" pin_yin="duan" sheng_diao="4" id="816" mistakes="0" times="0" xu_hao="13" qs="0"/>

      <zi han_zi="魂" pin_yin="hun" sheng_diao="2" id="648" mistakes="0" times="0" xu_hao="14" qs="0"/>

      <zi han_zi="。" pin_yin="" sheng_diao="" id="" mistakes="0" times="0" xu_hao="15" qs="0"/>

      <zi han_zi="借" pin_yin="jie" sheng_diao="4" id="439" mistakes="0" times="0" xu_hao="16" qs="0"/>

      <zi han_zi="问" pin_yin="wen" sheng_diao="4" id="126" mistakes="0" times="0" xu_hao="17" qs="0"/>

      <zi han_zi="酒" pin_yin="jiu" sheng_diao="3" id="965" mistakes="0" times="0" xu_hao="18" qs="0"/>

      <zi han_zi="家" pin_yin="jia" sheng_diao="1" id="1858" mistakes="0" times="0" xu_hao="19" qs="0"/>

      <zi han_zi="何" pin_yin="he" sheng_diao="2" id="1522" mistakes="0" times="0" xu_hao="20" qs="0"/>

      <zi han_zi="处" pin_yin="chu" sheng_diao="4" id="1979" mistakes="0" times="0" xu_hao="21" qs="0"/>

      <zi han_zi="有" pin_yin="you" sheng_diao="3" id="282" mistakes="0" times="0" xu_hao="22" qs="0"/>

      <zi han_zi="？" pin_yin="" sheng_diao="" id="" mistakes="0" times="0" xu_hao="23" qs="0"/>

      <zi han_zi="牧" pin_yin="mu" sheng_diao="4" id="894" mistakes="0" times="0" xu_hao="24" qs="0"/>

      <zi han_zi="童" pin_yin="tong" sheng_diao="2" id="908" mistakes="0" times="0" xu_hao="25" qs="0"/>

      <zi han_zi="遥" pin_yin="yao" sheng_diao="2" id="446" mistakes="0" times="0" xu_hao="26" qs="0"/>

      <zi han_zi="指" pin_yin="zhi" sheng_diao="3" id="" mistakes="0" times="0" xu_hao="27" qs="0"/>

      <zi han_zi="杏" pin_yin="xing" sheng_diao="4" id="" mistakes="0" times="0" xu_hao="28" qs="0"/>

      <zi han_zi="花" pin_yin="hua" sheng_diao="1" id="147" mistakes="0" times="0" xu_hao="29" qs="0"/>

      <zi han_zi="村" pin_yin="cun" sheng_diao="1" id="1638" mistakes="0" times="0" xu_hao="30" qs="0"/>

      <zi han_zi="。" pin_yin="" sheng_diao="" id="" mistakes="0" times="0" xu_hao="31" qs="0"/>

    </paragraph>

  </page>

</pages>

